crossapp/__init__.py
crossapp-0.1.0.dist-info/WHEEL
crossapp-0.1.0.dist-info/METADATA
crossapp-0.1.0.dist-info/RECORD
